test.py
nstreamai_nstream_ai/__init__.py
nstreamai_nstream_ai/core/__init__.py
nstreamai_nstream_ai/core/nsgraph.py
nstreamai_nstream_ai/core/nsinit.py
nstreamai_nstream_ai/core/nsneuron.py
nstreamai_nstream_ai/core/nsnode.py
nstreamai_nstream_ai/utils/__init__.py
nstreamai_nstream_ai/utils/logger.py
nstreamai_nstream_ai/utils/output_data.py
nstreamai_nstream_ai/utils/run.py
nstreamai_nstream_ai/utils/template.py
nstreamai_nstream_ai/utils/variables.py
nstreamai_nstream_ai/utils/welcome.py
nstreamai-0.0.15.dist-info/LICENSE
nstreamai-0.0.15.dist-info/METADATA
nstreamai-0.0.15.dist-info/WHEEL
nstreamai-0.0.15.dist-info/top_level.txt
nstreamai-0.0.15.dist-info/RECORD
