Metadata-Version: 2.1
Name: nstreamai
Version: 0.0.15
Summary: Official SDK for nstream ai stream processing powered by Gen AI
Home-page: https://github.com/nstream-ai/ms-public-sdk
Author: Nstream AI
Author-email: hello@nstream.ai
License: MIT
Keywords: nstreamai,streaming,rag,analytics,realtime
Classifier: License :: OSI Approved :: MIT License
Classifier: Programming Language :: Python :: 3
Classifier: Programming Language :: Python :: 3.7
Requires-Python: >=3.8, <4
License-File: LICENSE
Requires-Dist: annotated-types ==0.6.0
Requires-Dist: anyio ==4.3.0
Requires-Dist: certifi ==2024.2.2
Requires-Dist: charset-normalizer ==3.3.2
Requires-Dist: distro ==1.9.0
Requires-Dist: exceptiongroup ==1.2.0
Requires-Dist: h11 ==0.14.0
Requires-Dist: httpcore ==1.0.5
Requires-Dist: httpx ==0.27.0
Requires-Dist: idna ==3.7
Requires-Dist: openai ==1.19.0
Requires-Dist: pydantic ==2.7.0
Requires-Dist: pydantic-core ==2.18.1
Requires-Dist: pyfiglet ==1.0.2
Requires-Dist: requests ==2.31.0
Requires-Dist: sniffio ==1.3.1
Requires-Dist: termcolor ==2.4.0
Requires-Dist: tqdm ==4.66.2
Requires-Dist: typing-extensions ==4.11.0
Requires-Dist: urllib3 ==2.2.1
